{
  "date": "2026-04-24",
  "fund_code": "00981A",
  "total_nav": null,
  "holdings": [
    {
      "ticker": "2330",
      "name": "台積電",
      "weight": 9.39,
      "shares": 9114000
    },
    {
      "ticker": "2383",
      "name": "台光電",
      "weight": 8.7,
      "shares": 4125000
    },
    {
      "ticker": "2308",
      "name": "台達電",
      "weight": 5.89,
      "shares": 6024000
    },
    {
      "ticker": "3653",
      "name": "健策",
      "weight": 5.74,
      "shares": 2267000
    },
    {
      "ticker": "3017",
      "name": "奇鋐",
      "weight": 5.42,
      "shares": 3902000
    },
    {
      "ticker": "3665",
      "name": "貿聯-KY",
      "weight": 5.34,
      "shares": 4097848
    },
    {
      "ticker": "2345",
      "name": "智邦",
      "weight": 5.28,
      "shares": 5231000
    },
    {
      "ticker": "2368",
      "name": "金像電",
      "weight": 5.08,
      "shares": 7748000
    },
    {
      "ticker": "8046",
      "name": "南電",
      "weight": 4.9,
      "shares": 11881000
    },
    {
      "ticker": "2454",
      "name": "聯發科",
      "weight": 4.44,
      "shares": 3867000
    }
  ],
  "source": "moneydj"
}